berrosoft_upgrade/__init__.py
berrosoft_upgrade/bupgrade.py
berrosoft_upgrade-0.1.dist-info/METADATA
berrosoft_upgrade-0.1.dist-info/WHEEL
berrosoft_upgrade-0.1.dist-info/top_level.txt
berrosoft_upgrade-0.1.dist-info/RECORD
